Metadata-Version: 2.1
Name: py-jobject
Version: 0.1.0
Summary: A package to easily convert between Python objects and JSON-compatible dictionaries, with built-in type conversion.
Home-page: https://github.com/fcicc/py-jobject
Author: Fernando Cicconeto
Author-email: fcicconeto@gmail.com
License: UNKNOWN
Platform: UNKNOWN
Classifier: Programming Language :: Python :: 3.6
Classifier: License :: OSI Approved :: GNU General Public License v3 (GPLv3)
